{ "compressionlevel":-1,
 "editorsettings":
    {
     "export":
        {
         "format":"json",
         "target":"ts8_in1.json"
        }
    },
 "height":8,
 "infinite":false,
 "layers":[
        {
         "data":[641, 642, 642, 642, 642, 642, 642, 643, 93, 93, 93, 93, 93, 93, 93, 662, 93, 93, 93, 93, 93, 93, 93, 93, 93, 516, 518, 518, 519, 93, 93, 93, 93, 532, 534, 534, 535, 93, 93, 93, 93, 564, 566, 566, 567, 93, 93, 93, 93, 93, 93, 93, 93, 93, 93, 93, 673, 674, 674, 93, 93, 674, 674, 675],
         "height":8,
         "id":1,
         "name":"bg",
         "opacity":1,
         "properties":[
                {
                 "name":"layer_type",
                 "type":"string",
                 "value":"bg"
                }, 
                {
                 "name":"prio",
                 "type":"int",
                 "value":0
                }],
         "type":"tilelayer",
         "visible":true,
         "width":8,
         "x":0,
         "y":0
        }, 
        {
         "data":[0, 0, 0, 679, 689, 690, 679, 0, 657, 0, 0, 0, 0, 0, 0, 659, 657, 0, 0, 0, 0, 0, 0, 659, 657, 0, 0, 0, 0, 0, 0, 659, 657, 628, 629, 630, 627, 0, 661, 659, 657, 0, 0, 0, 0, 0, 0, 659, 657, 0, 0, 0, 0, 0, 0, 659, 0, 0, 0, 477, 477, 0, 0, 0],
         "height":8,
         "id":5,
         "name":"bg2",
         "opacity":1,
         "properties":[
                {
                 "name":"layer_type",
                 "type":"string",
                 "value":"bg"
                }, 
                {
                 "name":"prio",
                 "type":"int",
                 "value":1
                }],
         "type":"tilelayer",
         "visible":true,
         "width":8,
         "x":0,
         "y":0
        }, 
        {
         "data":[676, 677, 644, 0, 0, 0, 0, 0, 692, 693, 660, 0, 0, 0, 0, 0, 0, 0, 0, 0, 0, 0, 0, 0, 0, 0, 0, 0, 0, 0, 0, 0, 0, 0, 0, 0, 0, 0, 0, 0, 0, 0, 0, 0, 0, 0, 0, 0, 0, 0, 0, 0, 0, 0, 0, 0, 0, 0, 0, 0, 0, 0, 0, 0],
         "height":8,
         "id":6,
         "name":"bg3",
         "opacity":1,
         "properties":[
                {
                 "name":"layer_type",
                 "type":"string",
                 "value":"bg"
                }, 
                {
                 "name":"prio",
                 "type":"int",
                 "value":2
                }],
         "type":"tilelayer",
         "visible":true,
         "width":8,
         "x":0,
         "y":0
        }, 
        {
         "data":[0, 0, 0, 0, 0, 0, 0, 0, 0, 0, 0, 0, 0, 0, 0, 0, 0, 0, 0, 0, 0, 0, 0, 0, 0, 612, 613, 614, 611, 0, 645, 0, 0, 0, 0, 0, 0, 0, 0, 0, 0, 0, 0, 0, 0, 0, 0, 0, 0, 0, 0, 0, 0, 0, 0, 0, 0, 0, 0, 0, 0, 0, 0, 0],
         "height":8,
         "id":3,
         "name":"fg",
         "opacity":1,
         "properties":[
                {
                 "name":"layer_type",
                 "type":"string",
                 "value":"fg"
                }, 
                {
                 "name":"prio",
                 "type":"int",
                 "value":0
                }],
         "type":"tilelayer",
         "visible":true,
         "width":8,
         "x":0,
         "y":0
        }, 
        {
         "color":"#ff0000",
         "draworder":"topdown",
         "id":4,
         "name":"bounds",
         "objects":[
                {
                 "height":128,
                 "id":1,
                 "name":"",
                 "rotation":0,
                 "type":"",
                 "visible":true,
                 "width":4,
                 "x":0,
                 "y":0
                }, 
                {
                 "height":128,
                 "id":4,
                 "name":"",
                 "rotation":0,
                 "type":"",
                 "visible":true,
                 "width":4,
                 "x":124,
                 "y":0
                }, 
                {
                 "height":8,
                 "id":6,
                 "name":"",
                 "rotation":0,
                 "type":"",
                 "visible":true,
                 "width":120,
                 "x":4,
                 "y":0
                }, 
                {
                 "height":12,
                 "id":8,
                 "name":"",
                 "rotation":0,
                 "type":"",
                 "visible":true,
                 "width":44,
                 "x":4,
                 "y":12
                }, 
                {
                 "height":12,
                 "id":9,
                 "name":"",
                 "rotation":0,
                 "type":"",
                 "visible":true,
                 "width":64,
                 "x":16,
                 "y":64
                }, 
                {
                 "height":16,
                 "id":11,
                 "name":"",
                 "rotation":0,
                 "type":"",
                 "visible":true,
                 "width":44,
                 "x":4,
                 "y":112
                }, 
                {
                 "height":16,
                 "id":12,
                 "name":"",
                 "rotation":0,
                 "type":"",
                 "visible":true,
                 "width":44,
                 "x":80,
                 "y":112
                }, 
                {
                 "height":8,
                 "id":13,
                 "name":"",
                 "rotation":0,
                 "type":"",
                 "visible":true,
                 "width":16,
                 "x":96,
                 "y":64
                }],
         "opacity":1,
         "type":"objectgroup",
         "visible":true,
         "x":0,
         "y":0
        }, 
        {
         "color":"#55ff00",
         "draworder":"topdown",
         "id":9,
         "name":"dialogs",
         "objects":[
                {
                 "height":16,
                 "id":21,
                 "name":"",
                 "properties":[
                        {
                         "name":"max_chars",
                         "type":"int",
                         "value":10
                        }, 
                        {
                         "name":"n_lines",
                         "type":"int",
                         "value":3
                        }, 
                        {
                         "name":"text",
                         "type":"string",
                         "value":"WELL"
                        }],
                 "rotation":0,
                 "type":"",
                 "visible":true,
                 "width":16,
                 "x":32,
                 "y":16
                }],
         "opacity":1,
         "type":"objectgroup",
         "visible":true,
         "x":0,
         "y":0
        }, 
        {
         "color":"#0055ff",
         "draworder":"topdown",
         "id":8,
         "name":"teleports",
         "objects":[
                {
                 "height":0,
                 "id":15,
                 "name":"",
                 "properties":[
                        {
                         "name":"dest_frame",
                         "type":"int",
                         "value":0
                        }, 
                        {
                         "name":"dest_x",
                         "type":"int",
                         "value":128
                        }, 
                        {
                         "name":"dest_y",
                         "type":"int",
                         "value":128
                        }],
                 "rotation":0,
                 "type":"",
                 "visible":true,
                 "width":32,
                 "x":48,
                 "y":128
                }, 
                {
                 "height":16,
                 "id":17,
                 "name":"",
                 "properties":[
                        {
                         "name":"dest_frame",
                         "type":"int",
                         "value":2
                        }, 
                        {
                         "name":"dest_x",
                         "type":"int",
                         "value":16
                        }, 
                        {
                         "name":"dest_y",
                         "type":"int",
                         "value":24
                        }],
                 "rotation":0,
                 "type":"",
                 "visible":true,
                 "width":4,
                 "x":120,
                 "y":16
                }],
         "opacity":1,
         "type":"objectgroup",
         "visible":true,
         "x":0,
         "y":0
        }],
 "nextlayerid":10,
 "nextobjectid":22,
 "orientation":"orthogonal",
 "renderorder":"right-down",
 "tiledversion":"1.7.2",
 "tileheight":16,
 "tilesets":[
        {
         "firstgid":1,
         "source":"..\/..\/tilesets\/ts8_tr.tsx"
        }, 
        {
         "firstgid":257,
         "source":"..\/..\/tilesets\/ts8_br.tsx"
        }, 
        {
         "firstgid":513,
         "source":"..\/..\/tilesets\/ts8_in.tsx"
        }],
 "tilewidth":16,
 "type":"map",
 "version":"1.6",
 "width":8
}